cli.py
model.py
predict.py
utils/__init__.py
utils/authenticators.py
utils/constants.py
spinectl-0.2.7.dist-info/LICENSE.txt
spinectl-0.2.7.dist-info/METADATA
spinectl-0.2.7.dist-info/WHEEL
spinectl-0.2.7.dist-info/entry_points.txt
spinectl-0.2.7.dist-info/top_level.txt
spinectl-0.2.7.dist-info/RECORD
