Metadata-Version: 2.1
Name: spinectl
Version: 0.2.7
Summary: Dataspine CLI client
Home-page: https://github.com/dataspine
Author: Dataspine, Inc
Author-email: dev@dataspine.io
License: UNKNOWN
Platform: UNKNOWN
Requires-Dist: asn1crypto (==0.24.0)
Requires-Dist: basicauth (==0.4.1)
Requires-Dist: boto3 (==1.7.64)
Requires-Dist: botocore (==1.10.64)
Requires-Dist: cachetools (==2.1.0)
Requires-Dist: certifi (==2018.4.16)
Requires-Dist: chardet (==3.0.4)
Requires-Dist: click (==6.7)
Requires-Dist: docutils (==0.14)
Requires-Dist: entrypoints (==0.2.3)
Requires-Dist: fire (==0.1.3)
Requires-Dist: Flask (==1.0.2)
Requires-Dist: Flask-API (==1.0)
Requires-Dist: google-auth (==1.5.0)
Requires-Dist: idna (==2.7)
Requires-Dist: ipaddress (==1.0.22)
Requires-Dist: itsdangerous (==0.24)
Requires-Dist: Jinja2 (==2.11.0)
Requires-Dist: jmespath (==0.9.3)
Requires-Dist: jwt (==0.5.4)
Requires-Dist: kubernetes (==6.0.0)
Requires-Dist: oauthlib (==3.1.0)
Requires-Dist: pyasn1 (==0.4.4)
Requires-Dist: pyasn1-modules (==0.2.2)
Requires-Dist: pycparser (==2.18)
Requires-Dist: python-dateutil (==2.6.1)
Requires-Dist: pyyaml (==4.2b1)
Requires-Dist: requests (==2.20.0)
Requires-Dist: requests-oauthlib (==1.0.0)
Requires-Dist: rsa (==3.4.2)
Requires-Dist: s3transfer (==0.1.13)
Requires-Dist: shelljob (==0.5.6)
Requires-Dist: six (==1.11.0)
Requires-Dist: tabulate (==0.8.2)
Requires-Dist: urllib3 (==1.24.2)
Requires-Dist: websocket-client (==0.48.0)
Requires-Dist: werkzeug (>=0.15.3)
